pqt2_dev_req/__init__.py
pqt2_dev_req/calculate_method.py
pqt2_dev_req/database.py
pqt2_dev_req/database_operations.py
pqt2_dev_req/ddT.py
pqt2_dev_req/driagram.py
pqt2_dev_req/main.py
pqt2_dev_req/main_window.py
pqt2_dev_req/material_form.py
pqt2_dev_req/materials_list.py
pqt2_dev_req/sql.py
pqt2_dev_req/suppliers_tab.py
pqt2_dev_req-1.0.dist-info/METADATA
pqt2_dev_req-1.0.dist-info/WHEEL
pqt2_dev_req-1.0.dist-info/top_level.txt
pqt2_dev_req-1.0.dist-info/RECORD
